{"digraph": {"vertex_count": 34, "arc_count": 528, "arcs": [[0, 1, 1, 1, 1, 1, 1, 1, 1, 1, 1, 1, 1, 1, 1, 1, 1, 1, 1, 1, 1, 1, 1, 1, 1, 1, 1, 1, 1, 1, 1, 1, 1, 1], [0, 0, 1, 1, 1, 1, 1, 1, 1, 1, 1, 1, 1, 1, 1, 1, 1, 1, 1, 1, 1, 1, 1, 1, 1, 1, 1, 1, 1, 1, 1, 1, 1, 1], [0, 1, 0, 1, 1, 1, 1, 1, 1, 1, 1, 1, 1, 1, 1, 1, 1, 1, 1, 1, 1, 1, 1, 1, 1, 1, 1, 1, 1, 1, 1, 1, 1, 1], [0, 1, 1, 0, 1, 1, 1, 1, 1, 1, 1, 1, 1, 1, 1, 1, 1, 1, 1, 1, 1, 1, 1, 1, 1, 1, 1, 1, 1, 1, 1, 1, 1, 1], [0, 1, 1, 1, 0, 1, 1, 1, 1, 1, 1, 1, 1, 1, 1, 1, 1, 1, 1, 1, 1, 1, 1, 1, 1, 1, 1, 1, 1, 1, 1, 1, 1, 1], [0, 1, 1, 1, 1, 0, 1, 1, 1, 1, 1, 1, 1, 1, 1, 1, 1, 1, 1, 1, 1, 1, 1, 1, 1, 1, 1, 1, 1, 1, 1, 1, 1, 1], [0, 1, 1, 1, 1, 1, 0, 1, 1, 1, 1, 1, 1, 1, 1, 1, 1, 1, 1, 1, 1, 1, 1, 1, 1, 1, 1, 1, 1, 1, 1, 1, 1, 1], [0, 1, 1, 1, 1, 1, 1, 0, 1, 1, 1, 1, 1, 1, 1, 1, 1, 1, 1, 1, 1, 1, 1, 1, 1, 1, 1, 1, 1, 1, 1, 1, 1, 1], [0, 1, 1, 1, 1, 1, 1, 1, 0, 1, 1, 1, 1, 1, 1, 1, 1, 1, 1, 1, 1, 1, 1, 1, 1, 1, 1, 1, 1, 1, 1, 1, 1, 1], [0, 1, 1, 1, 1, 1, 1, 1, 1, 0, 1, 1, 1, 1, 1, 1, 1, 1, 1, 1, 1, 1, 1, 1, 1, 1, 1, 1, 1, 1, 1, 1, 1, 1], [0, 1, 1, 1, 1, 1, 1, 1, 1, 1, 0, 1, 1, 1, 1, 1, 1, 1, 1, 1, 1, 1, 1, 1, 1, 1, 1, 1, 1, 1, 1, 1, 1, 1], [0, 1, 1, 1, 1, 1, 1, 1, 1, 1, 1, 0, 1, 1, 1, 1, 1, 1, 1, 1, 1, 1, 1, 1, 1, 1, 1, 1, 1, 1, 1, 1, 1, 1], [0, 1, 1, 1, 1, 1, 1, 1, 1, 1, 1, 1, 0, 1, 1, 1, 1, 1, 1, 1, 1, 1, 1, 1, 1, 1, 1, 1, 1, 1, 1, 1, 1, 1], [0, 1, 1, 1, 1, 1, 1, 1, 1, 1, 1, 1, 1, 0, 1, 1, 1, 1, 1, 1, 1, 1, 1, 1, 1, 1, 1, 1, 1, 1, 1, 1, 1, 1], [0, 1, 1, 1, 1, 1, 1, 1, 1, 1, 1, 1, 1, 1, 0, 1, 1, 1, 1, 1, 1, 1, 1, 1, 1, 1, 1, 1, 1, 1, 1, 1, 1, 1], [0, 1, 1, 1, 1, 1, 1, 1, 1, 1, 1, 1, 1, 1, 1, 0, 1, 1, 1, 1, 1, 1, 1, 1, 1, 1, 1, 1, 1, 1, 1, 1, 1, 1], [0, 1, 1, 1, 1, 1, 1, 1, 1, 1, 1, 1, 1, 1, 1, 1, 0, 1, 1, 1, 1, 1, 1, 1, 1, 1, 1, 1, 1, 1, 1, 1, 1, 1], [0, 1, 1, 1, 1, 1, 1, 1, 1, 1, 1, 1, 1, 1, 1, 1, 1, 0, 1, 1, 1, 1, 1, 1, 1, 1, 1, 1, 1, 1, 1, 1, 1, 1], [0, 1, 1, 1, 1, 1, 1, 1, 1, 1, 1, 1, 1, 1, 1, 1, 1, 1, 0, 1, 1, 1, 1, 1, 1, 1, 1, 1, 1, 1, 1, 1, 1, 1], [0, 1, 1, 1, 1, 1, 1, 1, 1, 1, 1, 1, 1, 1, 1, 1, 1, 1, 1, 0, 1, 1, 1, 1, 1, 1, 1, 1, 1, 1, 1, 1, 1, 1], [0, 1, 1, 1, 1, 1, 1, 1, 1, 1, 1, 1, 1, 1, 1, 1, 1, 1, 1, 1, 0, 1, 1, 1, 1, 1, 1, 1, 1, 1, 1, 1, 1, 1], [0, 1, 1, 1, 1, 1, 1, 1, 1, 1, 1, 1, 1, 1, 1, 1, 1, 1, 1, 1, 1, 0, 1, 1, 1, 1, 1, 1, 1, 1, 1, 1, 1, 1], [0, 1, 1, 1, 1, 1, 1, 1, 1, 1, 1, 1, 1, 1, 1, 1, 1, 1, 1, 1, 1, 1, 0, 1, 1, 1, 1, 1, 1, 1, 1, 1, 1, 1], [0, 1, 1, 1, 1, 1, 1, 1, 1, 1, 1, 1, 1, 1, 1, 1, 1, 1, 1, 1, 1, 1, 1, 0, 1, 1, 1, 1, 1, 1, 1, 1, 1, 1], [0, 1, 1, 1, 1, 1, 1, 1, 1, 1, 1, 1, 1, 1, 1, 1, 1, 1, 1, 1, 1, 1, 1, 1, 0, 1, 1, 1, 1, 1, 1, 1, 1, 1], [0, 1, 1, 1, 1, 1, 1, 1, 1, 1, 1, 1, 1, 1, 1, 1, 1, 1, 1, 1, 1, 1, 1, 1, 1, 0, 1, 1, 1, 1, 1, 1, 1, 1], [0, 1, 1, 1, 1, 1, 1, 1, 1, 1, 1, 1, 1, 1, 1, 1, 1, 1, 1, 1, 1, 1, 1, 1, 1, 1, 0, 1, 1, 1, 1, 1, 1, 1], [0, 1, 1, 1, 1, 1, 1, 1, 1, 1, 1, 1, 1, 1, 1, 1, 1, 1, 1, 1, 1, 1, 1, 1, 1, 1, 1, 0, 1, 1, 1, 1, 1, 1], [0, 1, 1, 1, 1, 1, 1, 1, 1, 1, 1, 1, 1, 1, 1, 1, 1, 1, 1, 1, 1, 1, 1, 1, 1, 1, 1, 1, 0, 1, 1, 1, 1, 1], [0, 1, 1, 1, 1, 1, 1, 1, 1, 1, 1, 1, 1, 1, 1, 1, 1, 1, 1, 1, 1, 1, 1, 1, 1, 1, 1, 1, 1, 0, 1, 1, 1, 1], [0, 1, 1, 1, 1, 1, 1, 1, 1, 1, 1, 1, 1, 1, 1, 1, 1, 1, 1, 1, 1, 1, 1, 1, 1, 1, 1, 1, 1, 1, 0, 1, 1, 1], [0, 1, 1, 1, 1, 1, 1, 1, 1, 1, 1, 1, 1, 1, 1, 1, 1, 1, 1, 1, 1, 1, 1, 1, 1, 1, 1, 1, 1, 1, 1, 0, 1, 1], [0, 1, 1, 1, 1, 1, 1, 1, 1, 1, 1, 1, 1, 1, 1, 1, 1, 1, 1, 1, 1, 1, 1, 1, 1, 1, 1, 1, 1, 1, 1, 1, 0, 1], [0, 0, 0, 0, 0, 0, 0, 0, 0, 0, 0, 0, 0, 0, 0, 0, 0, 0, 0, 0, 0, 0, 0, 0, 0, 0, 0, 0, 0, 0, 0, 0, 0, 0]], "coordinates": [[40.0, 50.0], [22.0, 75.0], [20.0, 80.0], [44.0, 5.0], [42.0, 10.0], [42.0, 15.0], [40.0, 5.0], [40.0, 15.0], [38.0, 5.0], [67.0, 85.0], [65.0, 85.0], [65.0, 82.0], [60.0, 80.0], [55.0, 80.0], [42.0, 5.0], [42.0, 12.0], [25.0, 30.0], [55.0, 60.0], [30.0, 60.0], [50.0, 35.0], [15.0, 60.0], [65.0, 20.0], [41.0, 37.0], [40.0, 60.0], [35.0, 69.0], [65.0, 55.0], [63.0, 65.0], [60.0, 12.0], [49.0, 58.0], [57.0, 29.0], [12.0, 24.0], [67.0, 5.0], [31.0, 67.0], [40.0, 50.0]]}, "cluster_count": 3, "cluster_speeds": [[1.5, 1.0, 1.67, 1.17, 1.33], [1.17, 0.67, 1.33, 0.83, 1.0], [1.0, 0.33, 0.67, 0.5, 0.83]], "clusters": [[0, 2, 1, 0, 1, 1, 2, 0, 2, 0, 2, 0, 1, 1, 2, 0, 1, 1, 1, 2, 0, 2, 2, 0, 1, 0, 1, 0, 0, 0, 0, 1, 1, 1], [0, 1, 0, 0, 0, 0, 0, 1, 0, 2, 2, 1, 1, 0, 2, 0, 1, 1, 2, 0, 2, 1, 1, 2, 2, 1, 1, 1, 2, 2, 0, 1, 0, 0], [1, 0, 1, 1, 2, 1, 1, 0, 0, 2, 0, 0, 1, 0, 2, 0, 2, 1, 0, 1, 0, 1, 2, 0, 2, 1, 2, 0, 1, 1, 0, 2, 0, 0], [2, 0, 2, 2, 2, 0, 0, 1, 1, 1, 1, 0, 0, 1, 2, 1, 1, 1, 2, 0, 2, 1, 0, 1, 0, 1, 2, 2, 0, 0, 1, 2, 0, 0], [0, 2, 2, 1, 1, 1, 1, 1, 0, 2, 2, 1, 0, 2, 2, 0, 1, 0, 2, 2, 0, 1, 2, 2, 2, 2, 0, 1, 0, 2, 0, 0, 0, 2], [0, 2, 1, 0, 1, 2, 1, 2, 0, 0, 1, 2, 0, 2, 0, 1, 2, 0, 2, 2, 1, 2, 2, 2, 1, 2, 1, 2, 0, 1, 2, 1, 0, 0], [2, 2, 1, 2, 2, 2, 0, 0, 2, 2, 2, 2, 0, 2, 2, 0, 1, 1, 0, 0, 2, 1, 2, 2, 0, 0, 1, 0, 1, 2, 2, 2, 0, 1], [0, 1, 2, 2, 2, 0, 1, 0, 0, 1, 2, 0, 2, 2, 0, 0, 1, 1, 0, 1, 2, 2, 0, 0, 2, 1, 2, 0, 1, 1, 1, 1, 0, 0], [1, 0, 1, 2, 1, 0, 1, 1, 2, 2, 1, 2, 2, 0, 1, 0, 1, 0, 2, 1, 1, 0, 1, 0, 2, 2, 2, 1, 0, 0, 1, 2, 1, 0], [2, 0, 0, 2, 0, 0, 2, 2, 2, 0, 0, 1, 2, 1, 0, 1, 2, 1, 0, 0, 0, 1, 2, 0, 0, 2, 0, 0, 2, 1, 0, 2, 1, 2], [1, 2, 2, 0, 2, 2, 1, 0, 2, 2, 0, 0, 2, 1, 0, 1, 1, 0, 2, 0, 0, 1, 0, 2, 1, 0, 0, 0, 2, 0, 2, 1, 1, 0], [0, 0, 2, 0, 2, 1, 1, 2, 0, 2, 0, 0, 0, 0, 1, 1, 1, 0, 1, 1, 0, 2, 2, 1, 2, 0, 1, 0, 0, 1, 0, 1, 2, 0], [1, 2, 0, 0, 2, 1, 2, 0, 0, 2, 1, 2, 2, 2, 2, 1, 1, 0, 2, 2, 2, 0, 1, 2, 1, 2, 0, 1, 0, 0, 2, 0, 1, 2], [0, 0, 2, 1, 2, 0, 1, 2, 0, 1, 0, 1, 0, 2, 1, 2, 1, 2, 1, 1, 2, 0, 2, 0, 1, 0, 2, 2, 2, 0, 1, 2, 2, 1], [2, 0, 2, 2, 0, 2, 1, 0, 1, 0, 1, 0, 0, 1, 1, 0, 2, 2, 1, 1, 2, 1, 2, 2, 2, 0, 1, 1, 0, 0, 0, 2, 2, 0], [1, 0, 2, 1, 1, 0, 0, 2, 0, 2, 2, 0, 0, 0, 1, 0, 2, 2, 1, 2, 1, 2, 0, 2, 2, 2, 0, 0, 0, 2, 2, 0, 2, 0], [0, 2, 2, 1, 1, 0, 0, 1, 0, 2, 0, 1, 2, 1, 0, 0, 1, 1, 1, 0, 1, 0, 1, 2, 0, 1, 2, 2, 1, 2, 0, 0, 1, 0], [1, 2, 1, 0, 1, 2, 2, 2, 0, 2, 2, 2, 2, 1, 2, 2, 0, 0, 2, 2, 2, 1, 1, 0, 0, 2, 2, 0, 1, 1, 1, 0, 0, 2], [1, 2, 0, 2, 2, 0, 2, 0, 1, 2, 2, 0, 2, 0, 2, 1, 1, 1, 1, 2, 2, 0, 1, 1, 0, 2, 2, 0, 2, 2, 1, 1, 2, 0], [2, 0, 0, 1, 0, 0, 2, 1, 0, 2, 0, 1, 1, 1, 0, 0, 2, 0, 2, 0, 2, 0, 2, 1, 1, 1, 2, 1, 2, 1, 2, 2, 2, 2], [2, 2, 2, 2, 0, 1, 2, 2, 0, 1, 1, 2, 1, 0, 1, 1, 0, 2, 1, 1, 2, 0, 1, 1, 0, 1, 2, 1, 1, 0, 0, 2, 1, 0], [2, 0, 2, 0, 0, 2, 0, 1, 0, 2, 1, 1, 2, 2, 0, 0, 0, 2, 1, 0, 2, 1, 2, 2, 0, 1, 2, 1, 0, 1, 1, 0, 0, 2], [1, 0, 0, 2, 0, 1, 1, 2, 1, 0, 2, 0, 0, 2, 1, 0, 1, 1, 2, 1, 1, 2, 2, 2, 2, 2, 1, 2, 2, 2, 1, 0, 2, 0], [0, 2, 2, 1, 1, 2, 1, 1, 2, 0, 2, 0, 2, 1, 2, 1, 0, 2, 0, 0, 1, 1, 2, 1, 1, 2, 1, 2, 2, 1, 1, 0, 1, 0], [2, 0, 2, 0, 2, 0, 0, 0, 2, 2, 0, 1, 2, 2, 0, 0, 0, 2, 2, 2, 2, 2, 2, 1, 0, 1, 1, 2, 2, 1, 2, 2, 0, 1], [1, 1, 0, 0, 2, 0, 2, 1, 2, 1, 0, 0, 2, 1, 2, 0, 1, 1, 2, 2, 2, 1, 0, 1, 1, 0, 2, 0, 1, 1, 0, 0, 0, 2], [0, 1, 1, 0, 1, 0, 2, 0, 2, 1, 1, 0, 2, 0, 1, 2, 1, 1, 1, 1, 2, 0, 0, 1, 1, 2, 1, 1, 1, 2, 2, 0, 2, 0], [0, 1, 1, 1, 1, 1, 1, 0, 0, 1, 2, 2, 1, 2, 2, 0, 1, 1, 0, 2, 0, 0, 2, 2, 2, 2, 1, 0, 0, 0, 2, 0, 1, 0], [0, 1, 2, 1, 0, 1, 1, 2, 1, 0, 1, 0, 2, 0, 1, 1, 0, 1, 2, 0, 0, 2, 2, 1, 2, 0, 2, 0, 2, 1, 1, 0, 2, 0], [2, 2, 2, 1, 1, 1, 2, 0, 2, 0, 0, 0, 0, 1, 1, 2, 2, 2, 2, 1, 0, 0, 0, 2, 0, 1, 1, 0, 0, 1, 0, 2, 0, 1], [1, 1, 2, 0, 1, 0, 2, 2, 0, 1, 2, 2, 0, 2, 2, 1, 2, 0, 0, 2, 2, 2, 1, 0, 1, 0, 1, 2, 0, 2, 0, 1, 1, 1], [2, 1, 1, 2, 0, 1, 0, 2, 1, 0, 2, 0, 1, 0, 0, 2, 0, 2, 1, 1, 1, 0, 2, 1, 1, 1, 0, 0, 1, 2, 1, 1, 1, 1], [2, 1, 2, 0, 0, 1, 0, 0, 2, 1, 2, 0, 1, 1, 0, 1, 1, 0, 0, 0, 2, 1, 1, 1, 2, 0, 0, 0, 2, 0, 2, 1, 2, 2], [2, 0, 0, 0, 0, 0, 0, 2, 2, 1, 0, 1, 1, 0, 1, 0, 2, 1, 2, 1, 2, 0, 2, 2, 2, 2, 0, 0, 1, 2, 0, 0, 2, 2]], "speed_zone_count": 5, "speed_zones": [[0.0, 192.0], [192.0, 288.0], [288.0, 672.0], [672.0, 768.0], [768.0, 960.0]], "distances": [[0, 30, 35, 45, 40, 35, 45, 35, 45, 43, 43, 40, 36, 33, 45, 38, 25, 18, 14, 18, 26, 39, 13, 10, 19, 25, 27, 42, 12, 27, 38, 51, 19, 0], [30, 0, 5, 72, 67, 63, 72, 62, 71, 46, 44, 43, 38, 33, 72, 65, 45, 35, 17, 48, 16, 69, 42, 23, 14, 46, 42, 72, 31, 57, 51, 81, 12, 30], [35, 5, 0, 77, 72, 68, 77, 67, 76, 47, 45, 45, 40, 35, 77, 70, 50, 39, 22, 53, 20, 74, 47, 28, 18, 50, 45, 77, 35, 62, 56, 86, 17, 35], [45, 72, 77, 0, 5, 10, 4, 10, 6, 82, 82, 79, 76, 75, 2, 7, 31, 55, 56, 30, 61, 25, 32, 55, 64, 54, 62, 17, 53, 27, 37, 23, 62, 45], [40, 67, 72, 5, 0, 5, 5, 5, 6, 78, 77, 75, 71, 70, 5, 2, 26, 51, 51, 26, 56, 25, 27, 50, 59, 50, 58, 18, 48, 24, 33, 25, 57, 40], [35, 63, 68, 10, 5, 0, 10, 2, 10, 73, 72, 70, 66, 65, 10, 3, 22, 46, 46, 21, 52, 23, 22, 45, 54, 46, 53, 18, 43, 20, 31, 26, 53, 35], [45, 72, 77, 4, 5, 10, 0, 10, 2, 83, 82, 80, 76, 75, 2, 7, 29, 56, 55, 31, 60, 29, 32, 55, 64, 55, 63, 21, 53, 29, 33, 27, 62, 45], [35, 62, 67, 10, 5, 2, 10, 0, 10, 74, 73, 71, 67, 65, 10, 3, 21, 47, 46, 22, 51, 25, 22, 45, 54, 47, 54, 20, 43, 22, 29, 28, 52, 35], [45, 71, 76, 6, 6, 10, 2, 10, 0, 83, 82, 80, 76, 75, 4, 8, 28, 56, 55, 31, 59, 30, 32, 55, 64, 56, 63, 23, 53, 30, 32, 29, 62, 45], [43, 46, 47, 82, 78, 73, 83, 74, 83, 0, 2, 3, 8, 13, 83, 76, 68, 27, 44, 52, 56, 65, 53, 36, 35, 30, 20, 73, 31, 56, 81, 80, 39, 43], [43, 44, 45, 82, 77, 72, 82, 73, 82, 2, 0, 3, 7, 11, 82, 75, 67, 26, 43, 51, 55, 65, 52, 35, 33, 30, 20, 73, 31, 56, 80, 80, 37, 43], [40, 43, 45, 79, 75, 70, 80, 71, 80, 3, 3, 0, 5, 10, 80, 73, 64, 24, 41, 49, 53, 62, 50, 33, 32, 27, 17, 70, 28, 53, 78, 77, 36, 40], [36, 38, 40, 76, 71, 66, 76, 67, 76, 8, 7, 5, 0, 5, 76, 69, 60, 20, 36, 45, 48, 60, 46, 28, 27, 25, 15, 68, 24, 51, 73, 75, 31, 36], [33, 33, 35, 75, 70, 65, 75, 65, 75, 13, 11, 10, 5, 0, 75, 68, 58, 20, 32, 45, 43, 60, 44, 25, 22, 26, 17, 68, 22, 51, 70, 75, 26, 33], [45, 72, 77, 2, 5, 10, 2, 10, 4, 83, 82, 80, 76, 75, 0, 7, 30, 56, 56, 31, 61, 27, 32, 55, 64, 55, 63, 19, 53, 28, 35, 25, 62, 45], [38, 65, 70, 7, 2, 3, 7, 3, 8, 76, 75, 73, 69, 68, 7, 0, 24, 49, 49, 24, 54, 24, 25, 48, 57, 48, 56, 18, 46, 22, 32, 25, 55, 38], [25, 45, 50, 31, 26, 22, 29, 21, 28, 68, 67, 64, 60, 58, 30, 24, 0, 42, 30, 25, 31, 41, 17, 33, 40, 47, 51, 39, 36, 32, 14, 48, 37, 25], [18, 35, 39, 55, 51, 46, 56, 47, 56, 27, 26, 24, 20, 20, 56, 49, 42, 0, 25, 25, 40, 41, 26, 15, 21, 11, 9, 48, 6, 31, 56, 56, 25, 18], [14, 17, 22, 56, 51, 46, 55, 46, 55, 44, 43, 41, 36, 32, 56, 49, 30, 25, 0, 32, 15, 53, 25, 10, 10, 35, 33, 56, 19, 41, 40, 65, 7, 14], [18, 48, 53, 30, 26, 21, 31, 22, 31, 52, 51, 49, 45, 45, 31, 24, 25, 25, 32, 0, 43, 21, 9, 26, 36, 25, 32, 25, 23, 9, 39, 34, 37, 18], [26, 16, 20, 61, 56, 52, 60, 51, 59, 56, 55, 53, 48, 43, 61, 54, 31, 40, 15, 43, 0, 63, 34, 25, 21, 50, 48, 65, 34, 51, 36, 74, 17, 26], [39, 69, 74, 25, 25, 23, 29, 25, 30, 65, 65, 62, 60, 60, 27, 24, 41, 41, 53, 21, 63, 0, 29, 47, 57, 35, 45, 9, 41, 12, 53, 15, 58, 39], [13, 42, 47, 32, 27, 22, 32, 22, 32, 53, 52, 50, 46, 44, 32, 25, 17, 26, 25, 9, 34, 29, 0, 23, 32, 30, 35, 31, 22, 17, 31, 40, 31, 13], [10, 23, 28, 55, 50, 45, 55, 45, 55, 36, 35, 33, 28, 25, 55, 48, 33, 15, 10, 26, 25, 47, 23, 0, 10, 25, 23, 51, 9, 35, 45, 60, 11, 10], [19, 14, 18, 64, 59, 54, 64, 54, 64, 35, 33, 32, 27, 22, 64, 57, 40, 21, 10, 36, 21, 57, 32, 10, 0, 32, 28, 61, 17, 45, 50, 70, 4, 19], [25, 46, 50, 54, 50, 46, 55, 47, 56, 30, 30, 27, 25, 26, 55, 48, 47, 11, 35, 25, 50, 35, 30, 25, 32, 0, 10, 43, 16, 27, 61, 50, 36, 25], [27, 42, 45, 62, 58, 53, 63, 54, 63, 20, 20, 17, 15, 17, 63, 56, 51, 9, 33, 32, 48, 45, 35, 23, 28, 10, 0, 53, 15, 36, 65, 60, 32, 27], [42, 72, 77, 17, 18, 18, 21, 20, 23, 73, 73, 70, 68, 68, 19, 18, 39, 48, 56, 25, 65, 9, 31, 51, 61, 43, 53, 0, 47, 17, 49, 9, 61, 42], [12, 31, 35, 53, 48, 43, 53, 43, 53, 31, 31, 28, 24, 22, 53, 46, 36, 6, 19, 23, 34, 41, 22, 9, 17, 16, 15, 47, 0, 30, 50, 55, 20, 12], [27, 57, 62, 27, 24, 20, 29, 22, 30, 56, 56, 53, 51, 51, 28, 22, 32, 31, 41, 9, 51, 12, 17, 35, 45, 27, 36, 17, 30, 0, 45, 26, 46, 27], [38, 51, 56, 37, 33, 31, 33, 29, 32, 81, 80, 78, 73, 70, 35, 32, 14, 56, 40, 39, 36, 53, 31, 45, 50, 61, 65, 49, 50, 45, 0, 57, 47, 38], [51, 81, 86, 23, 25, 26, 27, 28, 29, 80, 80, 77, 75, 75, 25, 25, 48, 56, 65, 34, 74, 15, 40, 60, 70, 50, 60, 9, 55, 26, 57, 0, 70, 51], [19, 12, 17, 62, 57, 53, 62, 52, 62, 39, 37, 36, 31, 26, 62, 55, 37, 25, 7, 37, 17, 58, 31, 11, 4, 36, 32, 61, 20, 46, 47, 70, 0, 19], [0, 30, 35, 45, 40, 35, 45, 35, 45, 43, 43, 40, 36, 33, 45, 38, 25, 18, 14, 18, 26, 39, 13, 10, 19, 25, 27, 42, 12, 27, 38, 51, 19, 0]], "time_windows": [[0.0, 960.0], [0.0, 919.0], [644.0, 764.0], [0.0, 904.0], [0.0, 909.0], [0.0, 914.0], [0.0, 905.0], [375.0, 495.0], [201.0, 321.0], [657.0, 777.0], [43.0, 163.0], [0.0, 909.0], [64.0, 184.0], [33.0, 153.0], [0.0, 904.0], [440.0, 560.0], [0.0, 925.0], [0.0, 931.0], [599.0, 719.0], [557.0, 677.0], [0.0, 923.0], [0.0, 910.0], [566.0, 686.0], [612.0, 732.0], [810.0, 930.0], [0.0, 924.0], [0.0, 922.0], [268.0, 388.0], [0.0, 937.0], [395.0, 515.0], [359.0, 479.0], [0.0, 897.0], [810.0, 930.0], [0.0, 960.0]], "start_depot": 0, "end_depot": 33, "horizon": [0.0, 960.0]}